labeling/Labeling.py
labeling/LabelingData.py
labeling/__init__.py
test/__init__.py
test/test_labeling.py
test/test_labelingdata.py
labeling-0.1.14.dist-info/LICENSE
labeling-0.1.14.dist-info/METADATA
labeling-0.1.14.dist-info/WHEEL
labeling-0.1.14.dist-info/top_level.txt
labeling-0.1.14.dist-info/RECORD
