Metadata-Version: 2.1
Name: labeling
Version: 0.1.14
Summary: A package to create labeling/segmentation information based on pixel values.
Home-page: https://github.com/Labelings/pyLabeling
Author: Tom Burke
Author-email: 
Project-URL: Bug Tracker, https://github.com/Labelings/pyLabeling/issues
Classifier: Programming Language :: Python :: 3
Classifier: Development Status :: 4 - Beta
Classifier: Intended Audience :: Science/Research
Classifier: Topic :: Scientific/Engineering
Classifier: License :: OSI Approved :: BSD License
Classifier: Operating System :: OS Independent
Requires-Python: >=3.7
License-File: LICENSE
Requires-Dist: tifffile
Requires-Dist: pillow
Requires-Dist: numpy
Requires-Dist: scipy
Provides-Extra: dev
Requires-Dist: pytest ; extra == 'dev'
Requires-Dist: flake8 ; extra == 'dev'
